httpcloak/__init__.py
httpcloak/client.py
httpcloak/lib/libhttpcloak-linux-arm64.so
httpcloak-1.5.10.dist-info/METADATA
httpcloak-1.5.10.dist-info/WHEEL
httpcloak-1.5.10.dist-info/top_level.txt
httpcloak-1.5.10.dist-info/RECORD
