Metadata-Version: 2.4
Name: httpcloak
Version: 1.5.10
Summary: Browser fingerprint emulation HTTP client with HTTP/1.1, HTTP/2, and HTTP/3 support
License: MIT
Project-URL: Homepage, https://github.com/sardanioss/httpcloak
Project-URL: Documentation, https://github.com/sardanioss/httpcloak#readme
Project-URL: Repository, https://github.com/sardanioss/httpcloak
Project-URL: Issues, https://github.com/sardanioss/httpcloak/issues
Keywords: http,http2,http3,quic,tls,fingerprint,browser,scraping
Classifier: Development Status :: 4 - Beta
Classifier: Intended Audience :: Developers
Classifier: License :: OSI Approved :: MIT License
Classifier: Operating System :: OS Independent
Classifier: Programming Language :: Python :: 3
Classifier: Programming Language :: Python :: 3.8
Classifier: Programming Language :: Python :: 3.9
Classifier: Programming Language :: Python :: 3.10
Classifier: Programming Language :: Python :: 3.11
Classifier: Programming Language :: Python :: 3.12
Classifier: Topic :: Internet :: WWW/HTTP
Classifier: Topic :: Software Development :: Libraries :: Python Modules
Requires-Python: >=3.8
